drilling/__init__.py
drilling/conn.py
drilling/context.py
drilling/context_sources.py
drilling/dataset.py
drilling/libs.py
drilling-0.1.0.dist-info/METADATA
drilling-0.1.0.dist-info/WHEEL
drilling-0.1.0.dist-info/top_level.txt
drilling-0.1.0.dist-info/RECORD
