Metadata-Version: 2.4
Name: drilling
Version: 0.1.0
Summary: Lib para facilitar a manipulação de dados em projetos de Data Science
Author-email: Isaac Farias <zackfarias.pc@gmail.com>
License: MIT
Project-URL: Homepage, https://github.com/seuuser/minha-lib-top
Requires-Python: >=3.9
Requires-Dist: pandas<3.0,>=2.0
Requires-Dist: SQLAlchemy<3,>=1.4
Requires-Dist: PyYAML>=6.0
Requires-Dist: Unidecode>=1.3
Requires-Dist: google-api-python-client>=2.0
Requires-Dist: ipynbname>=2021.3.2
Requires-Dist: requests>=2.28
